[{
        "id": 1,
        "advertiser_id": null,
        "title": null,
        "size": null,
        "website": null,
        "image_url": "https://cdn.pixabay.com/photo/2016/09/04/20/14/sunset-1645105_960_720.jpg",
        "valid_from": "2020-02-25",
        "valid_to": "2020-05-25",
        "status": "CONFIRMED",
        "active": true
    },
    {
        "id": 2,
        "advertiser_id": null,
        "title": null,
        "size": null,
        "website": null,
        "image_url": "https://cdn.pixabay.com/photo/2017/10/03/17/53/nature-2813487_960_720.jpg",
        "valid_from": "2020-02-25",
        "valid_to": "2020-05-25",
        "status": "CONFIRMED",
        "active": true
    },
    {
        "id": 3,
        "advertiser_id": null,
        "title": null,
        "size": null,
        "website": "http://gora.si/",
        "image_url": "https://cdn.pixabay.com/photo/2016/03/06/17/39/banner-1240822_960_720.jpg",
        "valid_from": "2020-01-12",
        "valid_to": "2020-05-12",
        "status": "CONFIRMED",
        "active": true
    },
    {
        "id": 4,
        "advertiser_id": null,
        "title": null,
        "size": null,
        "website": null,
        "image_url": "https://cdn.pixabay.com/photo/2016/09/04/20/14/sunset-1645103_960_720.jpg",
        "valid_from": "2020-01-01",
        "valid_to": "2020-10-01",
        "status": "CONFIRMED",
        "active": true
    },
    {
        "id": 5,
        "advertiser_id": null,
        "title": null,
        "size": null,
        "website": null,
        "image_url": "https://cdn.pixabay.com/photo/2016/09/22/10/44/banner-1686943_960_720.jpg",
        "valid_from": "2020-01-01",
        "valid_to": "2020-10-01",
        "status": "CONFIRMED",
        "active": true
    }
]